{"week_id": "2026-W28", "label": "5.7 – 6.7.2026", "all": {"total_km": 28.028800000000004, "total_elev": 322.30000000000007, "run_count": 6, "athlete_count": 5, "leaderboard": [{"name": "Aaron Y.", "athlete_id": null, "km": 16.5, "elev": 121, "time": "1h 37m", "time_s": 5858, "acts": 2, "avg_speed": "10.6 km/h", "avg_speed_ms": 2.9541, "longest": 15.2, "gap": "leader", "ebike": false, "elev_per_km": 7.3, "unit": "", "company": ""}, {"name": "YU JUN ZE", "athlete_id": null, "km": 5.1, "elev": 121, "time": "0h 35m", "time_s": 2106, "acts": 1, "avg_speed": "8.7 km/h", "avg_speed_ms": 2.412, "longest": 5.1, "gap": "–11.4", "ebike": false, "elev_per_km": 23.9, "unit": "40SAR", "company": ""}, {"name": "Coriander S.", "athlete_id": null, "km": 2.6, "elev": 4, "time": "0h 20m", "time_s": 1241, "acts": 1, "avg_speed": "7.5 km/h", "avg_speed_ms": 2.0866, "longest": 2.6, "gap": "–13.9", "ebike": false, "elev_per_km": 1.5, "unit": "", "company": ""}, {"name": "Radra T.", "athlete_id": null, "km": 2.3, "elev": 61, "time": "0h 15m", "time_s": 916, "acts": 1, "avg_speed": "9.0 km/h", "avg_speed_ms": 2.4886, "longest": 2.3, "gap": "–14.2", "ebike": false, "elev_per_km": 26.8, "unit": "", "company": ""}, {"name": "TRUONG MINH QUAN", "athlete_id": null, "km": 1.6, "elev": 15, "time": "0h 8m", "time_s": 499, "acts": 1, "avg_speed": "11.5 km/h", "avg_speed_ms": 3.203, "longest": 1.6, "gap": "–14.9", "ebike": false, "elev_per_km": 9.3, "unit": "41SAR", "company": "Hawk"}, {"name": "AHMAD SALMAN ALFARISI BIN MAZLAN", "athlete_id": null, "km": 0.0, "elev": 0, "time": "0h 0m", "time_s": 0, "acts": 0, "avg_speed": "–", "avg_speed_ms": 0, "longest": 0.0, "gap": "–16.5", "ebike": false, "elev_per_km": null, "unit": "41SAR", "company": "Shrike"}, {"name": "TEO YEE ZER, ALFIE", "athlete_id": null, "km": 0.0, "elev": 0, "time": "0h 0m", "time_s": 0, "acts": 0, "avg_speed": "–", "avg_speed_ms": 0, "longest": 0.0, "gap": "–16.5", "ebike": false, "elev_per_km": null, "unit": "41SAR", "company": ""}, {"name": "HAN JIN YANG", "athlete_id": null, "km": 0.0, "elev": 0, "time": "0h 0m", "time_s": 0, "acts": 0, "avg_speed": "–", "avg_speed_ms": 0, "longest": 0.0, "gap": "–16.5", "ebike": false, "elev_per_km": null, "unit": "41SAR", "company": "Glory"}, {"name": "PONG AO ZHE", "athlete_id": null, "km": 0.0, "elev": 0, "time": "0h 0m", "time_s": 0, "acts": 0, "avg_speed": "–", "avg_speed_ms": 0, "longest": 0.0, "gap": "–16.5", "ebike": false, "elev_per_km": null, "unit": "41SAR", "company": "Shrike"}, {"name": "BENJAMIN NICODEMUS YEO", "athlete_id": null, "km": 0.0, "elev": 0, "time": "0h 0m", "time_s": 0, "acts": 0, "avg_speed": "–", "avg_speed_ms": 0, "longest": 0.0, "gap": "–16.5", "ebike": false, "elev_per_km": null, "unit": "41SAR", "company": "Hawk"}, {"name": "LAW BING XUN", "athlete_id": null, "km": 0.0, "elev": 0, "time": "0h 0m", "time_s": 0, "acts": 0, "avg_speed": "–", "avg_speed_ms": 0, "longest": 0.0, "gap": "–16.5", "ebike": false, "elev_per_km": null, "unit": "41SAR", "company": "Falcon"}, {"name": "Boy A.", "athlete_id": null, "km": 0.0, "elev": 0, "time": "0h 0m", "time_s": 0, "acts": 0, "avg_speed": "–", "avg_speed_ms": 0, "longest": 0.0, "gap": "–16.5", "ebike": false, "elev_per_km": null, "unit": "", "company": ""}, {"name": "Brandon T.", "athlete_id": null, "km": 0.0, "elev": 0, "time": "0h 0m", "time_s": 0, "acts": 0, "avg_speed": "–", "avg_speed_ms": 0, "longest": 0.0, "gap": "–16.5", "ebike": false, "elev_per_km": null, "unit": "", "company": ""}, {"name": "BRIAN TEO JIE QI", "athlete_id": null, "km": 0.0, "elev": 0, "time": "0h 0m", "time_s": 0, "acts": 0, "avg_speed": "–", "avg_speed_ms": 0, "longest": 0.0, "gap": "–16.5", "ebike": false, "elev_per_km": null, "unit": "41SAR", "company": "Shrike"}, {"name": "LIM CHER CHEE", "athlete_id": null, "km": 0.0, "elev": 0, "time": "0h 0m", "time_s": 0, "acts": 0, "avg_speed": "–", "avg_speed_ms": 0, "longest": 0.0, "gap": "–16.5", "ebike": false, "elev_per_km": null, "unit": "41SAR", "company": "Shrike"}, {"name": "Choon Yong C.", "athlete_id": null, "km": 0.0, "elev": 0, "time": "0h 0m", "time_s": 0, "acts": 0, "avg_speed": "–", "avg_speed_ms": 0, "longest": 0.0, "gap": "–16.5", "ebike": false, "elev_per_km": null, "unit": "", "company": ""}, {"name": "Christorf H.", "athlete_id": null, "km": 0.0, "elev": 0, "time": "0h 0m", "time_s": 0, "acts": 0, "avg_speed": "–", "avg_speed_ms": 0, "longest": 0.0, "gap": "–16.5", "ebike": false, "elev_per_km": null, "unit": "", "company": ""}, {"name": "GAN CHEE KAE", "athlete_id": null, "km": 0.0, "elev": 0, "time": "0h 0m", "time_s": 0, "acts": 0, "avg_speed": "–", "avg_speed_ms": 0, "longest": 0.0, "gap": "–16.5", "ebike": false, "elev_per_km": null, "unit": "41SAR", "company": "Shrike"}, {"name": "CLEMENT NG JIN XIANG", "athlete_id": null, "km": 0.0, "elev": 0, "time": "0h 0m", "time_s": 0, "acts": 0, "avg_speed": "–", "avg_speed_ms": 0, "longest": 0.0, "gap": "–16.5", "ebike": false, "elev_per_km": null, "unit": "41SAR", "company": "Shrike"}, {"name": "DALVIN SINGH S/O MANJIT SINGH", "athlete_id": null, "km": 0.0, "elev": 0, "time": "0h 0m", "time_s": 0, "acts": 0, "avg_speed": "–", "avg_speed_ms": 0, "longest": 0.0, "gap": "–16.5", "ebike": false, "elev_per_km": null, "unit": "41SAR", "company": "Shrike"}, {"name": "POH DE MING DAMIEN", "athlete_id": null, "km": 0.0, "elev": 0, "time": "0h 0m", "time_s": 0, "acts": 0, "avg_speed": "–", "avg_speed_ms": 0, "longest": 0.0, "gap": "–16.5", "ebike": false, "elev_per_km": null, "unit": "41SAR", "company": ""}, {"name": "Daniel Y.", "athlete_id": null, "km": 0.0, "elev": 0, "time": "0h 0m", "time_s": 0, "acts": 0, "avg_speed": "–", "avg_speed_ms": 0, "longest": 0.0, "gap": "–16.5", "ebike": false, "elev_per_km": null, "unit": "", "company": ""}, {"name": "DARSH PARMAR", "athlete_id": null, "km": 0.0, "elev": 0, "time": "0h 0m", "time_s": 0, "acts": 0, "avg_speed": "–", "avg_speed_ms": 0, "longest": 0.0, "gap": "–16.5", "ebike": false, "elev_per_km": null, "unit": "41SAR", "company": "Heron"}, {"name": "TAN CHENG KIAT DAVIAN", "athlete_id": null, "km": 0.0, "elev": 0, "time": "0h 0m", "time_s": 0, "acts": 0, "avg_speed": "–", "avg_speed_ms": 0, "longest": 0.0, "gap": "–16.5", "ebike": false, "elev_per_km": null, "unit": "41SAR", "company": "Hawk"}, {"name": "LIM YONG KANG, DENZEL", "athlete_id": null, "km": 0.0, "elev": 0, "time": "0h 0m", "time_s": 0, "acts": 0, "avg_speed": "–", "avg_speed_ms": 0, "longest": 0.0, "gap": "–16.5", "ebike": false, "elev_per_km": null, "unit": "41SAR", "company": "Hawk"}, {"name": "DONOVAN YUE SENG FONG", "athlete_id": null, "km": 0.0, "elev": 0, "time": "0h 0m", "time_s": 0, "acts": 0, "avg_speed": "–", "avg_speed_ms": 0, "longest": 0.0, "gap": "–16.5", "ebike": false, "elev_per_km": null, "unit": "41SAR", "company": "Shrike"}, {"name": "HUANG DINGTIAN", "athlete_id": null, "km": 0.0, "elev": 0, "time": "0h 0m", "time_s": 0, "acts": 0, "avg_speed": "–", "avg_speed_ms": 0, "longest": 0.0, "gap": "–16.5", "ebike": false, "elev_per_km": null, "unit": "41SAR", "company": ""}, {"name": "TAY EEWAN", "athlete_id": null, "km": 0.0, "elev": 0, "time": "0h 0m", "time_s": 0, "acts": 0, "avg_speed": "–", "avg_speed_ms": 0, "longest": 0.0, "gap": "–16.5", "ebike": false, "elev_per_km": null, "unit": "41SAR", "company": "Glory"}, {"name": "EMMANUEL CHAN KAI", "athlete_id": null, "km": 0.0, "elev": 0, "time": "0h 0m", "time_s": 0, "acts": 0, "avg_speed": "–", "avg_speed_ms": 0, "longest": 0.0, "gap": "–16.5", "ebike": false, "elev_per_km": null, "unit": "41SAR", "company": "Hawk"}, {"name": "Enoch T.", "athlete_id": null, "km": 0.0, "elev": 0, "time": "0h 0m", "time_s": 0, "acts": 0, "avg_speed": "–", "avg_speed_ms": 0, "longest": 0.0, "gap": "–16.5", "ebike": false, "elev_per_km": null, "unit": "", "company": ""}, {"name": "Ernest N.", "athlete_id": null, "km": 0.0, "elev": 0, "time": "0h 0m", "time_s": 0, "acts": 0, "avg_speed": "–", "avg_speed_ms": 0, "longest": 0.0, "gap": "–16.5", "ebike": false, "elev_per_km": null, "unit": "", "company": ""}, {"name": "LEE ERNST", "athlete_id": null, "km": 0.0, "elev": 0, "time": "0h 0m", "time_s": 0, "acts": 0, "avg_speed": "–", "avg_speed_ms": 0, "longest": 0.0, "gap": "–16.5", "ebike": false, "elev_per_km": null, "unit": "41SAR", "company": "Glory"}, {"name": "ETHAN YONG", "athlete_id": null, "km": 0.0, "elev": 0, "time": "0h 0m", "time_s": 0, "acts": 0, "avg_speed": "–", "avg_speed_ms": 0, "longest": 0.0, "gap": "–16.5", "ebike": false, "elev_per_km": null, "unit": "41SAR", "company": "Glory"}, {"name": "LIM SEE YEW, FELIX", "athlete_id": null, "km": 0.0, "elev": 0, "time": "0h 0m", "time_s": 0, "acts": 0, "avg_speed": "–", "avg_speed_ms": 0, "longest": 0.0, "gap": "–16.5", "ebike": false, "elev_per_km": null, "unit": "41SAR", "company": "Glory"}, {"name": "FITRI ADAM RYDAN BIN ESMADEE", "athlete_id": null, "km": 0.0, "elev": 0, "time": "0h 0m", "time_s": 0, "acts": 0, "avg_speed": "–", "avg_speed_ms": 0, "longest": 0.0, "gap": "–16.5", "ebike": false, "elev_per_km": null, "unit": "40SAR", "company": "Hercules"}, {"name": "JOHN GABRIEL CHEE", "athlete_id": null, "km": 0.0, "elev": 0, "time": "0h 0m", "time_s": 0, "acts": 0, "avg_speed": "–", "avg_speed_ms": 0, "longest": 0.0, "gap": "–16.5", "ebike": false, "elev_per_km": null, "unit": "41SAR", "company": "Shrike"}, {"name": "GU ZHAOYUAN", "athlete_id": null, "km": 0.0, "elev": 0, "time": "0h 0m", "time_s": 0, "acts": 0, "avg_speed": "–", "avg_speed_ms": 0, "longest": 0.0, "gap": "–16.5", "ebike": false, "elev_per_km": null, "unit": "41SAR", "company": ""}, {"name": "KOH ZIJIE, HAGAN", "athlete_id": null, "km": 0.0, "elev": 0, "time": "0h 0m", "time_s": 0, "acts": 0, "avg_speed": "–", "avg_speed_ms": 0, "longest": 0.0, "gap": "–16.5", "ebike": false, "elev_per_km": null, "unit": "41SAR", "company": "Shrike"}, {"name": "Ian C.", "athlete_id": null, "km": 0.0, "elev": 0, "time": "0h 0m", "time_s": 0, "acts": 0, "avg_speed": "–", "avg_speed_ms": 0, "longest": 0.0, "gap": "–16.5", "ebike": false, "elev_per_km": null, "unit": "", "company": ""}, {"name": "PHUA JIA WEI IAN", "athlete_id": null, "km": 0.0, "elev": 0, "time": "0h 0m", "time_s": 0, "acts": 0, "avg_speed": "–", "avg_speed_ms": 0, "longest": 0.0, "gap": "–16.5", "ebike": false, "elev_per_km": null, "unit": "41SAR", "company": ""}, {"name": "isaac B.", "athlete_id": null, "km": 0.0, "elev": 0, "time": "0h 0m", "time_s": 0, "acts": 0, "avg_speed": "–", "avg_speed_ms": 0, "longest": 0.0, "gap": "–16.5", "ebike": false, "elev_per_km": null, "unit": "", "company": ""}, {"name": "LEE JIN, ISAAC", "athlete_id": null, "km": 0.0, "elev": 0, "time": "0h 0m", "time_s": 0, "acts": 0, "avg_speed": "–", "avg_speed_ms": 0, "longest": 0.0, "gap": "–16.5", "ebike": false, "elev_per_km": null, "unit": "40SAR", "company": "Cougar"}, {"name": "LEE JIN, ISAAC", "athlete_id": null, "km": 0.0, "elev": 0, "time": "0h 0m", "time_s": 0, "acts": 0, "avg_speed": "–", "avg_speed_ms": 0, "longest": 0.0, "gap": "–16.5", "ebike": false, "elev_per_km": null, "unit": "40SAR", "company": "Cougar"}, {"name": "TAI YU XUAN, JADEN", "athlete_id": null, "km": 0.0, "elev": 0, "time": "0h 0m", "time_s": 0, "acts": 0, "avg_speed": "–", "avg_speed_ms": 0, "longest": 0.0, "gap": "–16.5", "ebike": false, "elev_per_km": null, "unit": "40SAR", "company": "Stallion"}, {"name": "Jason S.", "athlete_id": null, "km": 0.0, "elev": 0, "time": "0h 0m", "time_s": 0, "acts": 0, "avg_speed": "–", "avg_speed_ms": 0, "longest": 0.0, "gap": "–16.5", "ebike": false, "elev_per_km": null, "unit": "", "company": ""}, {"name": "JAYDEN LEE SUREDHRAN", "athlete_id": null, "km": 0.0, "elev": 0, "time": "0h 0m", "time_s": 0, "acts": 0, "avg_speed": "–", "avg_speed_ms": 0, "longest": 0.0, "gap": "–16.5", "ebike": false, "elev_per_km": null, "unit": "41SAR", "company": ""}, {"name": "JERAMY LOW JUN QI", "athlete_id": null, "km": 0.0, "elev": 0, "time": "0h 0m", "time_s": 0, "acts": 0, "avg_speed": "–", "avg_speed_ms": 0, "longest": 0.0, "gap": "–16.5", "ebike": false, "elev_per_km": null, "unit": "41SAR", "company": ""}, {"name": "KWOK YI JIE, JEREMY", "athlete_id": null, "km": 0.0, "elev": 0, "time": "0h 0m", "time_s": 0, "acts": 0, "avg_speed": "–", "avg_speed_ms": 0, "longest": 0.0, "gap": "–16.5", "ebike": false, "elev_per_km": null, "unit": "41SAR", "company": "Hawk"}, {"name": "LIM JING CHUAN", "athlete_id": null, "km": 0.0, "elev": 0, "time": "0h 0m", "time_s": 0, "acts": 0, "avg_speed": "–", "avg_speed_ms": 0, "longest": 0.0, "gap": "–16.5", "ebike": false, "elev_per_km": null, "unit": "41SAR", "company": "Glory"}, {"name": "TEO JING ZHE", "athlete_id": null, "km": 0.0, "elev": 0, "time": "0h 0m", "time_s": 0, "acts": 0, "avg_speed": "–", "avg_speed_ms": 0, "longest": 0.0, "gap": "–16.5", "ebike": false, "elev_per_km": null, "unit": "41SAR", "company": "Hawk"}, {"name": "NG JIU LIN", "athlete_id": null, "km": 0.0, "elev": 0, "time": "0h 0m", "time_s": 0, "acts": 0, "avg_speed": "–", "avg_speed_ms": 0, "longest": 0.0, "gap": "–16.5", "ebike": false, "elev_per_km": null, "unit": "41SAR", "company": ""}, {"name": "OH RUI XUN, JOEL", "athlete_id": null, "km": 0.0, "elev": 0, "time": "0h 0m", "time_s": 0, "acts": 0, "avg_speed": "–", "avg_speed_ms": 0, "longest": 0.0, "gap": "–16.5", "ebike": false, "elev_per_km": null, "unit": "40SAR", "company": "Stallion"}, {"name": "Joshua S.", "athlete_id": null, "km": 0.0, "elev": 0, "time": "0h 0m", "time_s": 0, "acts": 0, "avg_speed": "–", "avg_speed_ms": 0, "longest": 0.0, "gap": "–16.5", "ebike": false, "elev_per_km": null, "unit": "", "company": ""}, {"name": "WOO WEI CONG JOVAN", "athlete_id": null, "km": 0.0, "elev": 0, "time": "0h 0m", "time_s": 0, "acts": 0, "avg_speed": "–", "avg_speed_ms": 0, "longest": 0.0, "gap": "–16.5", "ebike": false, "elev_per_km": null, "unit": "41SAR", "company": "Glory"}, {"name": "LIM JING HENG JUDD", "athlete_id": null, "km": 0.0, "elev": 0, "time": "0h 0m", "time_s": 0, "acts": 0, "avg_speed": "–", "avg_speed_ms": 0, "longest": 0.0, "gap": "–16.5", "ebike": false, "elev_per_km": null, "unit": "41SAR", "company": "Glory"}, {"name": "JULIO NEO HUNG LI", "athlete_id": null, "km": 0.0, "elev": 0, "time": "0h 0m", "time_s": 0, "acts": 0, "avg_speed": "–", "avg_speed_ms": 0, "longest": 0.0, "gap": "–16.5", "ebike": false, "elev_per_km": null, "unit": "41SAR", "company": ""}, {"name": "CHEW JUN HAO", "athlete_id": null, "km": 0.0, "elev": 0, "time": "0h 0m", "time_s": 0, "acts": 0, "avg_speed": "–", "avg_speed_ms": 0, "longest": 0.0, "gap": "–16.5", "ebike": false, "elev_per_km": null, "unit": "40SAR", "company": "Cougar"}, {"name": "TENG JUN YONG", "athlete_id": null, "km": 0.0, "elev": 0, "time": "0h 0m", "time_s": 0, "acts": 0, "avg_speed": "–", "avg_speed_ms": 0, "longest": 0.0, "gap": "–16.5", "ebike": false, "elev_per_km": null, "unit": "41SAR", "company": "Hawk"}, {"name": "Kaelen W.", "athlete_id": null, "km": 0.0, "elev": 0, "time": "0h 0m", "time_s": 0, "acts": 0, "avg_speed": "–", "avg_speed_ms": 0, "longest": 0.0, "gap": "–16.5", "ebike": false, "elev_per_km": null, "unit": "", "company": ""}, {"name": "WONG KEI HANG", "athlete_id": null, "km": 0.0, "elev": 0, "time": "0h 0m", "time_s": 0, "acts": 0, "avg_speed": "–", "avg_speed_ms": 0, "longest": 0.0, "gap": "–16.5", "ebike": false, "elev_per_km": null, "unit": "41SAR", "company": "Hawk"}, {"name": "TAN KEK KUN KENNETH", "athlete_id": null, "km": 0.0, "elev": 0, "time": "0h 0m", "time_s": 0, "acts": 0, "avg_speed": "–", "avg_speed_ms": 0, "longest": 0.0, "gap": "–16.5", "ebike": false, "elev_per_km": null, "unit": "40SAR", "company": "Cougar"}, {"name": "KEVIN THOMAS", "athlete_id": null, "km": 0.0, "elev": 0, "time": "0h 0m", "time_s": 0, "acts": 0, "avg_speed": "–", "avg_speed_ms": 0, "longest": 0.0, "gap": "–16.5", "ebike": false, "elev_per_km": null, "unit": "41SAR", "company": "Shrike"}, {"name": "KIERAN KOH", "athlete_id": null, "km": 0.0, "elev": 0, "time": "0h 0m", "time_s": 0, "acts": 0, "avg_speed": "–", "avg_speed_ms": 0, "longest": 0.0, "gap": "–16.5", "ebike": false, "elev_per_km": null, "unit": "41SAR", "company": "Hawk"}, {"name": "TAN KIERAN", "athlete_id": null, "km": 0.0, "elev": 0, "time": "0h 0m", "time_s": 0, "acts": 0, "avg_speed": "–", "avg_speed_ms": 0, "longest": 0.0, "gap": "–16.5", "ebike": false, "elev_per_km": null, "unit": "41SAR", "company": "Shrike"}, {"name": "KISHEN M SUNTHARALINGAM", "athlete_id": null, "km": 0.0, "elev": 0, "time": "0h 0m", "time_s": 0, "acts": 0, "avg_speed": "–", "avg_speed_ms": 0, "longest": 0.0, "gap": "–16.5", "ebike": false, "elev_per_km": null, "unit": "41SAR", "company": ""}, {"name": "KUEK MING FENG", "athlete_id": null, "km": 0.0, "elev": 0, "time": "0h 0m", "time_s": 0, "acts": 0, "avg_speed": "–", "avg_speed_ms": 0, "longest": 0.0, "gap": "–16.5", "ebike": false, "elev_per_km": null, "unit": "41SAR", "company": "Hawk"}, {"name": "KWOH KAI JIE", "athlete_id": null, "km": 0.0, "elev": 0, "time": "0h 0m", "time_s": 0, "acts": 0, "avg_speed": "–", "avg_speed_ms": 0, "longest": 0.0, "gap": "–16.5", "ebike": false, "elev_per_km": null, "unit": "40SAR", "company": ""}, {"name": "LEE KA HAO", "athlete_id": null, "km": 0.0, "elev": 0, "time": "0h 0m", "time_s": 0, "acts": 0, "avg_speed": "–", "avg_speed_ms": 0, "longest": 0.0, "gap": "–16.5", "ebike": false, "elev_per_km": null, "unit": "41SAR", "company": "Hawk"}, {"name": "Liew K.", "athlete_id": null, "km": 0.0, "elev": 0, "time": "0h 0m", "time_s": 0, "acts": 0, "avg_speed": "–", "avg_speed_ms": 0, "longest": 0.0, "gap": "–16.5", "ebike": false, "elev_per_km": null, "unit": "", "company": ""}, {"name": "LIEW SHAN JUN", "athlete_id": null, "km": 0.0, "elev": 0, "time": "0h 0m", "time_s": 0, "acts": 0, "avg_speed": "–", "avg_speed_ms": 0, "longest": 0.0, "gap": "–16.5", "ebike": false, "elev_per_km": null, "unit": "41SAR", "company": "Hawk"}, {"name": "LIM PEI YING", "athlete_id": null, "km": 0.0, "elev": 0, "time": "0h 0m", "time_s": 0, "acts": 0, "avg_speed": "–", "avg_speed_ms": 0, "longest": 0.0, "gap": "–16.5", "ebike": false, "elev_per_km": null, "unit": "40SAR", "company": "Hercules"}, {"name": "LOH KIA FAI", "athlete_id": null, "km": 0.0, "elev": 0, "time": "0h 0m", "time_s": 0, "acts": 0, "avg_speed": "–", "avg_speed_ms": 0, "longest": 0.0, "gap": "–16.5", "ebike": false, "elev_per_km": null, "unit": "8SAB", "company": "Comd Office"}, {"name": "LUCAS CHENG WEI CHENG", "athlete_id": null, "km": 0.0, "elev": 0, "time": "0h 0m", "time_s": 0, "acts": 0, "avg_speed": "–", "avg_speed_ms": 0, "longest": 0.0, "gap": "–16.5", "ebike": false, "elev_per_km": null, "unit": "41SAR", "company": "Hawk"}, {"name": "LUCAS LEE KAY EONG", "athlete_id": null, "km": 0.0, "elev": 0, "time": "0h 0m", "time_s": 0, "acts": 0, "avg_speed": "–", "avg_speed_ms": 0, "longest": 0.0, "gap": "–16.5", "ebike": false, "elev_per_km": null, "unit": "41SAR", "company": "Glory"}, {"name": "luke ..", "athlete_id": null, "km": 0.0, "elev": 0, "time": "0h 0m", "time_s": 0, "acts": 0, "avg_speed": "–", "avg_speed_ms": 0, "longest": 0.0, "gap": "–16.5", "ebike": false, "elev_per_km": null, "unit": "", "company": ""}, {"name": "Luke C.", "athlete_id": null, "km": 0.0, "elev": 0, "time": "0h 0m", "time_s": 0, "acts": 0, "avg_speed": "–", "avg_speed_ms": 0, "longest": 0.0, "gap": "–16.5", "ebike": false, "elev_per_km": null, "unit": "", "company": ""}, {"name": "MUHAMMAD MANAZIL BIN SADIQUE JAFFER", "athlete_id": null, "km": 0.0, "elev": 0, "time": "0h 0m", "time_s": 0, "acts": 0, "avg_speed": "–", "avg_speed_ms": 0, "longest": 0.0, "gap": "–16.5", "ebike": false, "elev_per_km": null, "unit": "40SAR", "company": "Cougar"}, {"name": "MUHAMMAD SAIFULLAH BIN RIDHWAN", "athlete_id": null, "km": 0.0, "elev": 0, "time": "0h 0m", "time_s": 0, "acts": 0, "avg_speed": "–", "avg_speed_ms": 0, "longest": 0.0, "gap": "–16.5", "ebike": false, "elev_per_km": null, "unit": "41SAR", "company": ""}, {"name": "MUHAMMAD FARIS BIN MOHD SHARIFF", "athlete_id": null, "km": 0.0, "elev": 0, "time": "0h 0m", "time_s": 0, "acts": 0, "avg_speed": "–", "avg_speed_ms": 0, "longest": 0.0, "gap": "–16.5", "ebike": false, "elev_per_km": null, "unit": "41SAR", "company": "Shrike"}, {"name": "Ong J.", "athlete_id": null, "km": 0.0, "elev": 0, "time": "0h 0m", "time_s": 0, "acts": 0, "avg_speed": "–", "avg_speed_ms": 0, "longest": 0.0, "gap": "–16.5", "ebike": false, "elev_per_km": null, "unit": "", "company": ""}, {"name": "RYAN CHIN JIN KAI", "athlete_id": null, "km": 0.0, "elev": 0, "time": "0h 0m", "time_s": 0, "acts": 0, "avg_speed": "–", "avg_speed_ms": 0, "longest": 0.0, "gap": "–16.5", "ebike": false, "elev_per_km": null, "unit": "41SAR", "company": "Shrike"}, {"name": "NURUL RIFQAH A'ARISYA BINTE ISSEY HAMID", "athlete_id": null, "km": 0.0, "elev": 0, "time": "0h 0m", "time_s": 0, "acts": 0, "avg_speed": "–", "avg_speed_ms": 0, "longest": 0.0, "gap": "–16.5", "ebike": false, "elev_per_km": null, "unit": "41SAR", "company": "Heron"}, {"name": "S NARVIND", "athlete_id": null, "km": 0.0, "elev": 0, "time": "0h 0m", "time_s": 0, "acts": 0, "avg_speed": "–", "avg_speed_ms": 0, "longest": 0.0, "gap": "–16.5", "ebike": false, "elev_per_km": null, "unit": "40SAR", "company": "Hercules"}, {"name": "SANJEEV SARAVANAN", "athlete_id": null, "km": 0.0, "elev": 0, "time": "0h 0m", "time_s": 0, "acts": 0, "avg_speed": "–", "avg_speed_ms": 0, "longest": 0.0, "gap": "–16.5", "ebike": false, "elev_per_km": null, "unit": "41SAR", "company": "Shrike"}, {"name": "SHIV ANAND PATEL", "athlete_id": null, "km": 0.0, "elev": 0, "time": "0h 0m", "time_s": 0, "acts": 0, "avg_speed": "–", "avg_speed_ms": 0, "longest": 0.0, "gap": "–16.5", "ebike": false, "elev_per_km": null, "unit": "40SAR", "company": "Cougar"}, {"name": "R N SIVA KRISHNA", "athlete_id": null, "km": 0.0, "elev": 0, "time": "0h 0m", "time_s": 0, "acts": 0, "avg_speed": "–", "avg_speed_ms": 0, "longest": 0.0, "gap": "–16.5", "ebike": false, "elev_per_km": null, "unit": "40SAR", "company": "Hercules"}, {"name": "Syazani M.", "athlete_id": null, "km": 0.0, "elev": 0, "time": "0h 0m", "time_s": 0, "acts": 0, "avg_speed": "–", "avg_speed_ms": 0, "longest": 0.0, "gap": "–16.5", "ebike": false, "elev_per_km": null, "unit": "", "company": ""}, {"name": "TAN JED", "athlete_id": null, "km": 0.0, "elev": 0, "time": "0h 0m", "time_s": 0, "acts": 0, "avg_speed": "–", "avg_speed_ms": 0, "longest": 0.0, "gap": "–16.5", "ebike": false, "elev_per_km": null, "unit": "41SAR", "company": ""}, {"name": "Tang Z.", "athlete_id": null, "km": 0.0, "elev": 0, "time": "0h 0m", "time_s": 0, "acts": 0, "avg_speed": "–", "avg_speed_ms": 0, "longest": 0.0, "gap": "–16.5", "ebike": false, "elev_per_km": null, "unit": "", "company": ""}, {"name": "TIMOTHY CHOY CHENG EN", "athlete_id": null, "km": 0.0, "elev": 0, "time": "0h 0m", "time_s": 0, "acts": 0, "avg_speed": "–", "avg_speed_ms": 0, "longest": 0.0, "gap": "–16.5", "ebike": false, "elev_per_km": null, "unit": "40SAR", "company": "Stallion"}, {"name": "TNG KAI LIANG LONNARD", "athlete_id": null, "km": 0.0, "elev": 0, "time": "0h 0m", "time_s": 0, "acts": 0, "avg_speed": "–", "avg_speed_ms": 0, "longest": 0.0, "gap": "–16.5", "ebike": false, "elev_per_km": null, "unit": "41SAR", "company": "Shrike"}, {"name": "Unfit To F.", "athlete_id": null, "km": 0.0, "elev": 0, "time": "0h 0m", "time_s": 0, "acts": 0, "avg_speed": "–", "avg_speed_ms": 0, "longest": 0.0, "gap": "–16.5", "ebike": false, "elev_per_km": null, "unit": "", "company": ""}, {"name": "VERRAL VEE HUNG CHUN", "athlete_id": null, "km": 0.0, "elev": 0, "time": "0h 0m", "time_s": 0, "acts": 0, "avg_speed": "–", "avg_speed_ms": 0, "longest": 0.0, "gap": "–16.5", "ebike": false, "elev_per_km": null, "unit": "41SAR", "company": "Glory"}, {"name": "WAYNE CHAN KAI XUAN", "athlete_id": null, "km": 0.0, "elev": 0, "time": "0h 0m", "time_s": 0, "acts": 0, "avg_speed": "–", "avg_speed_ms": 0, "longest": 0.0, "gap": "–16.5", "ebike": false, "elev_per_km": null, "unit": "41SAR", "company": ""}, {"name": "Weikiang A.", "athlete_id": null, "km": 0.0, "elev": 0, "time": "0h 0m", "time_s": 0, "acts": 0, "avg_speed": "–", "avg_speed_ms": 0, "longest": 0.0, "gap": "–16.5", "ebike": false, "elev_per_km": null, "unit": "", "company": ""}, {"name": "LEE YU CHEN XAVIER", "athlete_id": null, "km": 0.0, "elev": 0, "time": "0h 0m", "time_s": 0, "acts": 0, "avg_speed": "–", "avg_speed_ms": 0, "longest": 0.0, "gap": "–16.5", "ebike": false, "elev_per_km": null, "unit": "41SAR", "company": ""}, {"name": "CHIA YU HENG ALVIN", "athlete_id": null, "km": 0.0, "elev": 0, "time": "0h 0m", "time_s": 0, "acts": 0, "avg_speed": "–", "avg_speed_ms": 0, "longest": 0.0, "gap": "–16.5", "ebike": false, "elev_per_km": null, "unit": "41SAR", "company": "Falcon"}, {"name": "yong huat T.", "athlete_id": null, "km": 0.0, "elev": 0, "time": "0h 0m", "time_s": 0, "acts": 0, "avg_speed": "–", "avg_speed_ms": 0, "longest": 0.0, "gap": "–16.5", "ebike": false, "elev_per_km": null, "unit": "", "company": ""}, {"name": "YongLe H.", "athlete_id": null, "km": 0.0, "elev": 0, "time": "0h 0m", "time_s": 0, "acts": 0, "avg_speed": "–", "avg_speed_ms": 0, "longest": 0.0, "gap": "–16.5", "ebike": false, "elev_per_km": null, "unit": "", "company": ""}, {"name": "DAVIEN ZANON CHEAH", "athlete_id": null, "km": 0.0, "elev": 0, "time": "0h 0m", "time_s": 0, "acts": 0, "avg_speed": "–", "avg_speed_ms": 0, "longest": 0.0, "gap": "–16.5", "ebike": false, "elev_per_km": null, "unit": "40SAR", "company": "Cougar"}, {"name": "TAN ZE XUAN", "athlete_id": null, "km": 0.0, "elev": 0, "time": "0h 0m", "time_s": 0, "acts": 0, "avg_speed": "–", "avg_speed_ms": 0, "longest": 0.0, "gap": "–16.5", "ebike": false, "elev_per_km": null, "unit": "41SAR", "company": ""}, {"name": "LOW ZENG XI", "athlete_id": null, "km": 0.0, "elev": 0, "time": "0h 0m", "time_s": 0, "acts": 0, "avg_speed": "–", "avg_speed_ms": 0, "longest": 0.0, "gap": "–16.5", "ebike": false, "elev_per_km": null, "unit": "41SAR", "company": ""}, {"name": "ZhiJin T.", "athlete_id": null, "km": 0.0, "elev": 0, "time": "0h 0m", "time_s": 0, "acts": 0, "avg_speed": "–", "avg_speed_ms": 0, "longest": 0.0, "gap": "–16.5", "ebike": false, "elev_per_km": null, "unit": "", "company": ""}, {"name": "WANG ZIXUAN", "athlete_id": null, "km": 0.0, "elev": 0, "time": "0h 0m", "time_s": 0, "acts": 0, "avg_speed": "–", "avg_speed_ms": 0, "longest": 0.0, "gap": "–16.5", "ebike": false, "elev_per_km": null, "unit": "40SAR", "company": "Stallion"}, {"name": "LU ZIKANG", "athlete_id": null, "km": 0.0, "elev": 0, "time": "0h 0m", "time_s": 0, "acts": 0, "avg_speed": "–", "avg_speed_ms": 0, "longest": 0.0, "gap": "–16.5", "ebike": false, "elev_per_km": null, "unit": "41SAR", "company": "Hawk"}, {"name": "ROWSHAN MUSHARRAF", "athlete_id": null, "km": 0.0, "elev": 0, "time": "0h 0m", "time_s": 0, "acts": 0, "avg_speed": "–", "avg_speed_ms": 0, "longest": 0.0, "gap": "–16.5", "ebike": false, "elev_per_km": null, "unit": "41SAR", "company": ""}], "fun_stats": {"virtual": null, "ebike": null, "breaks": {"name": "Coriander S.", "value": "19 min of rest"}}, "king_km": {"name": "Aaron Y.", "athlete_id": null, "value": "16.5 km"}, "king_elev": {"name": "YU JUN ZE", "athlete_id": null, "value": "121 m elevation"}, "marathoner": {"name": "Aaron Y.", "athlete_id": null, "value": "1h 37m"}, "fastest": {"name": "TRUONG MINH QUAN", "athlete_id": null, "value": "11.5 km/h"}, "longest": {"name": "Aaron Y.", "athlete_id": null, "value": "15.2 km"}, "climber": null, "flatrunner": null, "device_stats": [{"device": "COROS PACE 4", "count": 1}, {"device": "Polar Pacer", "count": 1}, {"device": "Strava App", "count": 3}], "label": "5.7 – 6.7.2026", "count": 6}}